mcp_md_pdf-0.1.0.dist-info/licenses/LICENSE
md_pdf_mcp/__init__.py
md_pdf_mcp/converter.py
md_pdf_mcp/server.py
mcp_md_pdf-0.1.0.dist-info/METADATA
mcp_md_pdf-0.1.0.dist-info/WHEEL
mcp_md_pdf-0.1.0.dist-info/entry_points.txt
mcp_md_pdf-0.1.0.dist-info/top_level.txt
mcp_md_pdf-0.1.0.dist-info/RECORD
