Metadata-Version: 2.4
Name: mcp-md-pdf
Version: 0.1.0
Summary: Model Context Protocol server for Markdown to Word/PDF conversion with template support
Author-email: Basel <basel@example.com>
Project-URL: Homepage, https://github.com/sham-devs/mcp-md-pdf
Project-URL: Repository, https://github.com/sham-devs/mcp-md-pdf
Project-URL: Issues, https://github.com/sham-devs/mcp-md-pdf/issues
Keywords: mcp,markdown,pdf,word,docx,converter,fastmcp
Classifier: Development Status :: 4 - Beta
Classifier: Intended Audience :: Developers
Classifier: License :: OSI Approved :: MIT License
Classifier: Programming Language :: Python :: 3
Classifier: Programming Language :: Python :: 3.10
Classifier: Programming Language :: Python :: 3.11
Classifier: Programming Language :: Python :: 3.12
Requires-Python: >=3.10
License-File: LICENSE
Requires-Dist: fastmcp>=0.1.0
Requires-Dist: pillow>=10.0.0
Requires-Dist: python-docx>=1.1.0
Requires-Dist: pywin32>=306; platform_system == "Windows"
Provides-Extra: dev
Requires-Dist: pytest>=7.0.0; extra == "dev"
Requires-Dist: pytest-cov>=4.0.0; extra == "dev"
Requires-Dist: psutil>=5.9.0; extra == "dev"
Requires-Dist: black>=23.0.0; extra == "dev"
Requires-Dist: ruff>=0.1.0; extra == "dev"
Dynamic: license-file
